qpl_py/__init__.py
qpl_py/_modidx.py
qpl_py/structs.py
qpl_py-0.0.2.dist-info/LICENSE
qpl_py-0.0.2.dist-info/METADATA
qpl_py-0.0.2.dist-info/WHEEL
qpl_py-0.0.2.dist-info/entry_points.txt
qpl_py-0.0.2.dist-info/top_level.txt
qpl_py-0.0.2.dist-info/RECORD
